rspystreamer/__init__.py
rspystreamer/consumer.py
rspystreamer/sender.py
rspystreamer/utils.py
rspystreamer-0.1.0.dist-info/METADATA
rspystreamer-0.1.0.dist-info/WHEEL
rspystreamer-0.1.0.dist-info/RECORD
