Metadata-Version: 2.3
Name: rspystreamer
Version: 0.1.0
Summary: A package to send and receive messages using Redis streams
License: MIT
Author: Reza Shirazi
Author-email: itreza7@gmail.com
Requires-Python: >=3.11,<4.0
Classifier: License :: OSI Approved :: MIT License
Classifier: Programming Language :: Python :: 3
Classifier: Programming Language :: Python :: 3.11
Classifier: Programming Language :: Python :: 3.12
Classifier: Programming Language :: Python :: 3.13
Requires-Dist: rspyredis (>=0.1.2,<1.0.0)
Project-URL: Repository, https://github.com/itreza7/rspystreamer
